conntextual/__init__.py
conntextual/__main__.py
conntextual/app.py
conntextual/client.py
conntextual/dev_requirements.txt
conntextual/entry.py
conntextual/py.typed
conntextual/requirements.txt
conntextual/server.py
conntextual/util.py
conntextual/commands/__init__.py
conntextual/commands/all.py
conntextual/commands/client.py
conntextual/commands/common.py
conntextual/commands/ui.py
conntextual/curses/__init__.py
conntextual/curses/base.py
conntextual/curses/tui.py
conntextual/data/app.yaml
conntextual/data/curses.yaml
conntextual/data/headless.yaml
conntextual/data/json.yaml
conntextual/data/sample.yaml
conntextual/data/tcss/base.tcss
conntextual/ui/__init__.py
conntextual/ui/base.py
conntextual/ui/footer.py
conntextual/ui/model.py
conntextual/ui/task.py
conntextual/ui/channel/__init__.py
conntextual/ui/channel/color.py
conntextual/ui/channel/environment.py
conntextual/ui/channel/log.py
conntextual/ui/channel/model.py
conntextual/ui/channel/pattern.py
conntextual/ui/channel/plot.py
conntextual/ui/channel/selected.py
conntextual/ui/channel/suggester.py
conntextual-1.3.6.dist-info/licenses/LICENSE
conntextual-1.3.6.dist-info/METADATA
conntextual-1.3.6.dist-info/WHEEL
conntextual-1.3.6.dist-info/entry_points.txt
conntextual-1.3.6.dist-info/top_level.txt
conntextual-1.3.6.dist-info/RECORD
