Metadata-Version: 2.4
Name: conntextual
Version: 1.3.6
Summary: A network-application TUI using textual.
Home-page: https://github.com/vkottler/conntextual
Author: Vaughn Kottler
Author-email: Vaughn Kottler <vaughn@libre-embedded.com>
Maintainer-email: Vaughn Kottler <vaughn@libre-embedded.com>
License-Expression: MIT
Classifier: Programming Language :: Python :: 3.12
Classifier: Programming Language :: Python :: 3.13
Classifier: Operating System :: MacOS
Classifier: Operating System :: POSIX :: Linux
Classifier: Operating System :: Unix
Classifier: Development Status :: 5 - Production/Stable
Requires-Python: >=3.12
License-File: LICENSE
Requires-Dist: textual
Requires-Dist: runtimepy>=5.14.2
Requires-Dist: vcorelib>=3.6.1
Requires-Dist: uvloop
Requires-Dist: psutil
Requires-Dist: numpy
Requires-Dist: textual-plotext
Requires-Dist: aiohttp>=3.9.0b0
Provides-Extra: test
Requires-Dist: pylint; extra == "test"
Requires-Dist: flake8; extra == "test"
Requires-Dist: black; extra == "test"
Requires-Dist: ruff; extra == "test"
Requires-Dist: mypy; extra == "test"
Requires-Dist: isort; extra == "test"
Requires-Dist: yamllint; extra == "test"
Requires-Dist: yambs; extra == "test"
Requires-Dist: vmklib>=2.0.3; extra == "test"
Requires-Dist: sphinx; extra == "test"
Requires-Dist: sphinx-book-theme; extra == "test"
Requires-Dist: setuptools-wrapper; extra == "test"
Requires-Dist: types-psutil; extra == "test"
Requires-Dist: types-setuptools; extra == "test"
Dynamic: author
Dynamic: home-page
Dynamic: license-file
Dynamic: requires-dist
Dynamic: requires-python
